{"Name":"Kevin Taylor","Address":"953 Dominguez Brooks\nMurrayview, IN 41268","Email":"mckenzieelaine@example.org","Phone Number":"+1-432-942-8864x885"}
{"Name":"Tracy Jones","Address":"USNS James\nFPO AA 25676","Email":"chasegreen@example.com","Phone Number":"782-505-4865"}
{"Name":"Allen May","Address":"43141 Hunter Ferry\nSouth Kathy, SD 26609","Email":"brooksdebbie@example.org","Phone Number":"9797593798"}
{"Name":"William Caldwell","Address":"09260 Keith Expressway Apt. 091\nNorth Paigeburgh, DC 95054","Email":"fisherstephanie@example.net","Phone Number":"+1-577-773-1169x22896"}
{"Name":"Adam Ruiz","Address":"PSC 8313, Box 2098\nAPO AP 31969","Email":"melissamacias@example.com","Phone Number":"+1-222-297-7956x66909"}
{"Name":"Brian Mcdonald","Address":"4046 Wright Prairie\nNorth Victorfurt, GA 38178","Email":"brittany08@example.com","Phone Number":"907.998.6960x6276"}
{"Name":"Joseph Buck","Address":"569 Angela Port\nWest Kari, LA 79847","Email":"nduarte@example.com","Phone Number":"+1-841-818-5325x355"}
{"Name":"Grant Key","Address":"32581 Lawrence Green Suite 572\nMelissachester, SC 62522","Email":"maryrichardson@example.org","Phone Number":"+1-559-532-5531x83574"}
{"Name":"Juan Serrano","Address":"05966 Wood Plains\nMckinneyview, AZ 26703","Email":"barbarajenkins@example.org","Phone Number":"697.703.8746"}
{"Name":"Matthew Thompson","Address":"PSC 5285, Box 3971\nAPO AE 25195","Email":"martinezjohn@example.com","Phone Number":"420-741-9352x36378"}
